[
  {
    "street_address": "1 Andrássy út",
    "street_name": "Andrássy út",
    "building_number": "1",
    "city": "Budapest",
    "state": "Budapest",
    "postal_code": "1061",
    "country": "Hungary",
    "country_code": "HU",
    "currency": "HUF",
    "person_name": "Tamás Kovács",
    "gender": "Male",
    "phone_number": "+3612345678"
  },
  {
    "street_address": "12 Váci utca",
    "street_name": "Váci utca",
    "building_number": "12",
    "city": "Budapest",
    "state": "Budapest",
    "postal_code": "1052",
    "country": "Hungary",
    "country_code": "HU",
    "currency": "HUF",
    "person_name": "Anna Szabó",
    "gender": "Female",
    "phone_number": "+3612345679"
  },
  {
    "street_address": "25 Széchenyi utca",
    "street_name": "Széchenyi utca",
    "building_number": "25",
    "city": "Budapest",
    "state": "Budapest",
    "postal_code": "1051",
    "country": "Hungary",
    "country_code": "HU",
    "currency": "HUF",
    "person_name": "Péter Nagy",
    "gender": "Male",
    "phone_number": "+3612345680"
  },
  {
    "street_address": "8 Kossuth Lajos utca",
    "street_name": "Kossuth Lajos utca",
    "building_number": "8",
    "city": "Budapest",
    "state": "Budapest",
    "postal_code": "1055",
    "country": "Hungary",
    "country_code": "HU",
    "currency": "HUF",
    "person_name": "Eszter Tóth",
    "gender": "Female",
    "phone_number": "+3612345681"
  },
  {
    "street_address": "34 Rákóczi út",
    "street_name": "Rákóczi út",
    "building_number": "34",
    "city": "Budapest",
    "state": "Budapest",
    "postal_code": "1072",
    "country": "Hungary",
    "country_code": "HU",
    "currency": "HUF",
    "person_name": "Gábor Horváth",
    "gender": "Male",
    "phone_number": "+3612345682"
  },
  {
    "street_address": "15 Bajcsy-Zsilinszky út",
    "street_name": "Bajcsy-Zsilinszky út",
    "building_number": "15",
    "city": "Budapest",
    "state": "Budapest",
    "postal_code": "1065",
    "country": "Hungary",
    "country_code": "HU",
    "currency": "HUF",
    "person_name": "Katalin Varga",
    "gender": "Female",
    "phone_number": "+3612345683"
  },
  {
    "street_address": "67 Erzsébet körút",
    "street_name": "Erzsébet körút",
    "building_number": "67",
    "city": "Budapest",
    "state": "Budapest",
    "postal_code": "1073",
    "country": "Hungary",
    "country_code": "HU",
    "currency": "HUF",
    "person_name": "László Molnár",
    "gender": "Male",
    "phone_number": "+3612345684"
  },
  {
    "street_address": "23 József körút",
    "street_name": "József körút",
    "building_number": "23",
    "city": "Budapest",
    "state": "Budapest",
    "postal_code": "1085",
    "country": "Hungary",
    "country_code": "HU",
    "currency": "HUF",
    "person_name": "Zsuzsanna Kiss",
    "gender": "Female",
    "phone_number": "+3612345685"
  },
  {
    "street_address": "45 Üllői út",
    "street_name": "Üllői út",
    "building_number": "45",
    "city": "Budapest",
    "state": "Budapest",
    "postal_code": "1094",
    "country": "Hungary",
    "country_code": "HU",
    "currency": "HUF",
    "person_name": "Miklós Farkas",
    "gender": "Male",
    "phone_number": "+3612345686"
  },
  {
    "street_address": "89 Bartók Béla út",
    "street_name": "Bartók Béla út",
    "building_number": "89",
    "city": "Budapest",
    "state": "Budapest",
    "postal_code": "1114",
    "country": "Hungary",
    "country_code": "HU",
    "currency": "HUF",
    "person_name": "Júlia Balogh",
    "gender": "Female",
    "phone_number": "+3612345687"
  },
  {
    "street_address": "12 Kossuth Lajos utca",
    "street_name": "Kossuth Lajos utca",
    "building_number": "12",
    "city": "Debrecen",
    "state": "Hajdú-Bihar County",
    "postal_code": "4024",
    "country": "Hungary",
    "country_code": "HU",
    "currency": "HUF",
    "person_name": "István Papp",
    "gender": "Male",
    "phone_number": "+3612345688"
  },
  {
    "street_address": "56 Piac utca",
    "street_name": "Piac utca",
    "building_number": "56",
    "city": "Debrecen",
    "state": "Hajdú-Bihar County",
    "postal_code": "4024",
    "country": "Hungary",
    "country_code": "HU",
    "currency": "HUF",
    "person_name": "Emese Nagy",
    "gender": "Female",
    "phone_number": "+3612345689"
  },
  {
    "street_address": "78 Csapó utca",
    "street_name": "Csapó utca",
    "building_number": "78",
    "city": "Debrecen",
    "state": "Hajdú-Bihar County",
    "postal_code": "4024",
    "country": "Hungary",
    "country_code": "HU",
    "currency": "HUF",
    "person_name": "Zoltán Tóth",
    "gender": "Male",
    "phone_number": "+3612345690"
  },
  {
    "street_address": "21 Hatvan utca",
    "street_name": "Hatvan utca",
    "building_number": "21",
    "city": "Debrecen",
    "state": "Hajdú-Bihar County",
    "postal_code": "4024",
    "country": "Hungary",
    "country_code": "HU",
    "currency": "HUF",
    "person_name": "Réka Kovács",
    "gender": "Female",
    "phone_number": "+3612345691"
  },
  {
    "street_address": "34 Bem tér",
    "street_name": "Bem tér",
    "building_number": "34",
    "city": "Szeged",
    "state": "Csongrád-Csanád County",
    "postal_code": "6720",
    "country": "Hungary",
    "country_code": "HU",
    "currency": "HUF",
    "person_name": "Balázs Szabo",
    "gender": "Male",
    "phone_number": "+3612345692"
  },
  {
    "street_address": "67 Kálvin tér",
    "street_name": "Kálvin tér",
    "building_number": "67",
    "city": "Szeged",
    "state": "Csongrád-Csanád County",
    "postal_code": "6720",
    "country": "Hungary",
    "country_code": "HU",
    "currency": "HUF",
    "person_name": "Orsolya Varga",
    "gender": "Female",
    "phone_number": "+3612345693"
  },
  {
    "street_address": "89 Tisza Lajos körút",
    "street_name": "Tisza Lajos körút",
    "building_number": "89",
    "city": "Szeged",
    "state": "Csongrád-Csanád County",
    "postal_code": "6720",
    "country": "Hungary",
    "country_code": "HU",
    "currency": "HUF",
    "person_name": "Ákos Molnár",
    "gender": "Male",
    "phone_number": "+3612345694"
  },
  {
    "street_address": "23 Széchenyi tér",
    "street_name": "Széchenyi tér",
    "building_number": "23",
    "city": "Szeged",
    "state": "Csongrád-Csanád County",
    "postal_code": "6720",
    "country": "Hungary",
    "country_code": "HU",
    "currency": "HUF",
    "person_name": "Erika Kiss",
    "gender": "Female",
    "phone_number": "+3612345695"
  },
  {
    "street_address": "45 Fő fasor",
    "street_name": "Fő fasor",
    "city": "Pécs",
    "state": "Baranya County",
    "postal_code": "7624",
    "country": "Hungary",
    "country_code": "HU",
    "currency": "HUF",
    "person_name": "Bence Horváth",
    "gender": "Male",
    "phone_number": "+3612345696"
  },
  {
    "street_address": "12 Király utca",
    "street_name": "Király utca",
    "building_number": "12",
    "city": "Pécs",
    "state": "Baranya County",
    "postal_code": "7624",
    "country": "Hungary",
    "country_code": "HU",
    "currency": "HUF",
    "person_name": "Dóra Nagy",
    "gender": "Female",
    "phone_number": "+3612345697"
  },
  {
    "street_address": "56 Széchenyi tér",
    "street_name": "Széchenyi tér",
    "building_number": "56",
    "city": "Pécs",
    "state": "Baranya County",
    "postal_code": "7624",
    "country": "Hungary",
    "country_code": "HU",
    "currency": "HUF",
    "person_name": "Máté Kovács",
    "gender": "Male",
    "phone_number": "+3612345698"
  },
  {
    "street_address": "78 Janus Pannonius utca",
    "street_name": "Janus Pannonius utca",
    "building_number": "78",
    "city": "Pécs",
    "state": "Baranya County",
    "postal_code": "7624",
    "country": "Hungary",
    "country_code": "HU",
    "currency": "HUF",
    "person_name": "Anikó Tóth",
    "gender": "Female",
    "phone_number": "+3612345699"
  },
  {
    "street_address": "34 Kossuth Lajos utca",
    "street_name": "Kossuth Lajos utca",
    "building_number": "34",
    "city": "Győr",
    "state": "Győr-Moson-Sopron County",
    "postal_code": "9022",
    "country": "Hungary",
    "country_code": "HU",
    "currency": "HUF",
    "person_name": "Gergő Szabó",
    "gender": "Male",
    "phone_number": "+3612345700"
  }
]