[
  {
    "street_address": "1 Avenida Central",
    "street_name": "Avenida Central",
    "building_number": "1",
    "city": "San José",
    "state": "San José",
    "postal_code": "10101",
    "country": "Costa Rica",
    "country_code": "CR",
    "currency": "CRC",
    "person_name": "Juan Morales",
    "gender": "Male",
    "phone_number": "+50670123456"
  },
  {
    "street_address": "12 Calle 5",
    "street_name": "Calle 5",
    "building_number": "12",
    "city": "San José",
    "state": "San José",
    "postal_code": "10101",
    "country": "Costa Rica",
    "country_code": "CR",
    "currency": "CRC",
    "person_name": "María Vargas",
    "gender": "Female",
    "phone_number": "+50670123457"
  },
  {
    "street_address": "25 Avenida 2",
    "street_name": "Avenida 2",
    "building_number": "25",
    "city": "San José",
    "state": "San José",
    "postal_code": "10101",
    "country": "Costa Rica",
    "country_code": "CR",
    "currency": "CRC",
    "person_name": "Carlos Gómez",
    "gender": "Male",
    "phone_number": "+50670123458"
  },
  {
    "street_address": "8 Calle Central",
    "street_name": "Calle Central",
    "building_number": "8",
    "city": "San José",
    "state": "San José",
    "postal_code": "10101",
    "country": "Costa Rica",
    "country_code": "CR",
    "currency": "CRC",
    "person_name": "Ana Rodríguez",
    "gender": "Female",
    "phone_number": "+50670123459"
  },
  {
    "street_address": "34 Avenida 10",
    "street_name": "Avenida 10",
    "building_number": "34",
    "city": "San José",
    "state": "San José",
    "postal_code": "10101",
    "country": "Costa Rica",
    "country_code": "CR",
    "currency": "CRC",
    "person_name": "Luis Fernández",
    "gender": "Male",
    "phone_number": "+50670123460"
  },
  {
    "street_address": "15 Calle 3",
    "street_name": "Calle 3",
    "building_number": "15",
    "city": "San José",
    "state": "San José",
    "postal_code": "10101",
    "country": "Costa Rica",
    "country_code": "CR",
    "currency": "CRC",
    "person_name": "Sofía López",
    "gender": "Female",
    "phone_number": "+50670123461"
  },
  {
    "street_address": "67 Avenida 8",
    "street_name": "Avenida 8",
    "building_number": "67",
    "city": "San José",
    "state": "San José",
    "postal_code": "10101",
    "country": "Costa Rica",
    "country_code": "CR",
    "currency": "CRC",
    "person_name": "Diego Ramírez",
    "gender": "Male",
    "phone_number": "+50670123462"
  },
  {
    "street_address": "23 Calle 7",
    "street_name": "Calle 7",
    "building_number": "23",
    "city": "San José",
    "state": "San José",
    "postal_code": "10101",
    "country": "Costa Rica",
    "country_code": "CR",
    "currency": "CRC",
    "person_name": "Clara Torres",
    "gender": "Female",
    "phone_number": "+50670123463"
  },
  {
    "street_address": "45 Avenida 4",
    "street_name": "Avenida 4",
    "building_number": "45",
    "city": "San José",
    "state": "San José",
    "postal_code": "10101",
    "country": "Costa Rica",
    "country_code": "CR",
    "currency": "CRC",
    "person_name": "Andrés Castro",
    "gender": "Male",
    "phone_number": "+50670123464"
  },
  {
    "street_address": "89 Calle 9",
    "street_name": "Calle 9",
    "building_number": "89",
    "city": "San José",
    "state": "San José",
    "postal_code": "10101",
    "country": "Costa Rica",
    "country_code": "CR",
    "currency": "CRC",
    "person_name": "Laura Sánchez",
    "gender": "Female",
    "phone_number": "+50670123465"
  },
  {
    "street_address": "12 Avenida Escazú",
    "street_name": "Avenida Escazú",
    "building_number": "12",
    "city": "Escazú",
    "state": "San José",
    "postal_code": "10201",
    "country": "Costa Rica",
    "country_code": "CR",
    "currency": "CRC",
    "person_name": "Javier Pérez",
    "gender": "Male",
    "phone_number": "+50670123466"
  },
  {
    "street_address": "56 Calle Ancha",
    "street_name": "Calle Ancha",
    "building_number": "56",
    "city": "Escazú",
    "state": "San José",
    "postal_code": "10201",
    "country": "Costa Rica",
    "country_code": "CR",
    "currency": "CRC",
    "person_name": "Isabel Monge",
    "gender": "Female",
    "phone_number": "+50670123467"
  },
  {
    "street_address": "78 Avenida Principal",
    "street_name": "Avenida Principal",
    "building_number": "78",
    "city": "Heredia",
    "state": "Heredia",
    "postal_code": "40101",
    "country": "Costa Rica",
    "country_code": "CR",
    "currency": "CRC",
    "person_name": "Gabriel Rojas",
    "gender": "Male",
    "phone_number": "+50670123468"
  },
  {
    "street_address": "21 Calle Central",
    "street_name": "Calle Central",
    "building_number": "21",
    "city": "Heredia",
    "state": "Heredia",
    "postal_code": "40101",
    "country": "Costa Rica",
    "country_code": "CR",
    "currency": "CRC",
    "person_name": "Valeria Arias",
    "gender": "Female",
    "phone_number": "+50670123469"
  },
  {
    "street_address": "34 Avenida 1",
    "street_name": "Avenida 1",
    "building_number": "34",
    "city": "Heredia",
    "state": "Heredia",
    "postal_code": "40101",
    "country": "Costa Rica",
    "country_code": "CR",
    "currency": "CRC",
    "person_name": "Esteban Campos",
    "gender": "Male",
    "phone_number": "+50670123470"
  },
  {
    "street_address": "67 Calle 2",
    "street_name": "Calle 2",
    "building_number": "67",
    "city": "Alajuela",
    "state": "Alajuela",
    "postal_code": "20101",
    "country": "Costa Rica",
    "country_code": "CR",
    "currency": "CRC",
    "person_name": "Camila Solís",
    "gender": "Female",
    "phone_number": "+50670123471"
  },
  {
    "street_address": "89 Avenida 3",
    "street_name": "Avenida 3",
    "building_number": "89",
    "city": "Alajuela",
    "state": "Alajuela",
    "postal_code": "20101",
    "country": "Costa Rica",
    "country_code": "CR",
    "currency": "CRC",
    "person_name": "Mateo Delgado",
    "gender": "Male",
    "phone_number": "+50670123472"
  },
  {
    "street_address": "23 Calle 4",
    "street_name": "Calle 4",
    "building_number": "23",
    "city": "Alajuela",
    "state": "Alajuela",
    "postal_code": "20101",
    "country": "Costa Rica",
    "country_code": "CR",
    "currency": "CRC",
    "person_name": "Fernanda Quirós",
    "gender": "Female",
    "phone_number": "+50670123473"
  },
  {
    "street_address": "45 Avenida 5",
    "street_name": "Avenida 5",
    "building_number": "45",
    "city": "Liberia",
    "state": "Guanacaste",
    "postal_code": "50101",
    "country": "Costa Rica",
    "country_code": "CR",
    "currency": "CRC",
    "person_name": "Rodrigo Salazar",
    "gender": "Male",
    "phone_number": "+50670123474"
  },
  {
    "street_address": "12 Calle Principal",
    "street_name": "Calle Principal",
    "building_number": "12",
    "city": "Liberia",
    "state": "Guanacaste",
    "postal_code": "50101",
    "country": "Costa Rica",
    "country_code": "CR",
    "currency": "CRC",
    "person_name": "Daniela Cordero",
    "gender": "Female",
    "phone_number": "+50670123475"
  },
  {
    "street_address": "56 Avenida Central",
    "street_name": "Avenida Central",
    "building_number": "56",
    "city": "Puntarenas",
    "state": "Puntarenas",
    "postal_code": "60101",
    "country": "Costa Rica",
    "country_code": "CR",
    "currency": "CRC",
    "person_name": "Sebastián Brenes",
    "gender": "Male",
    "phone_number": "+50670123476"
  },
  {
    "street_address": "78 Calle 1",
    "street_name": "Calle 1",
    "building_number": "78",
    "city": "Puntarenas",
    "state": "Puntarenas",
    "postal_code": "60101",
    "country": "Costa Rica",
    "country_code": "CR",
    "currency": "CRC",
    "person_name": "Gabriela Murillo",
    "gender": "Female",
    "phone_number": "+50670123477"
  },
  {
    "street_address": "34 Avenida del Mar",
    "street_name": "Avenida del Mar",
    "building_number": "34",
    "city": "Quepos",
    "state": "Puntarenas",
    "postal_code": "60601",
    "country": "Costa Rica",
    "country_code": "CR",
    "currency": "CRC",
    "person_name": "Alejandro Vega",
    "gender": "Male",
    "phone_number": "+50670123478"
  }
]