[
  {
    "street_address": "13 Brīvības iela",
    "street_name": "Brīvības iela",
    "building_number": "13",
    "city": "Riga",
    "state": "Riga",
    "postal_code": "LV-1010",
    "country": "Latvia",
    "country_code": "LV",
    "currency": "EUR",
    "person_name": "Jānis Bērziņš",
    "gender": "Male",
    "phone_number": "+37126123456"
  },
  {
    "street_address": "45 Lāčplēša iela",
    "street_name": "Lāčplēša iela",
    "building_number": "45",
    "city": "Riga",
    "state": "Riga",
    "postal_code": "LV-1010",
    "country": "Latvia",
    "country_code": "LV",
    "currency": "EUR",
    "person_name": "Anna Kalniņa",
    "gender": "Female",
    "phone_number": "+37126123457"
  },
  {
    "street_address": "78 Krasta iela",
    "street_name": "Krasta iela",
    "building_number": "78",
    "city": "Riga",
    "state": "Riga",
    "postal_code": "LV-1010",
    "country": "Latvia",
    "country_code": "LV",
    "currency": "EUR",
    "person_name": "Kārlis Ozoliņš",
    "gender": "Male",
    "phone_number": "+37126123458"
  },
  {
    "street_address": "34 Tērbatas iela",
    "street_name": "Tērbatas iela",
    "building_number": "34",
    "city": "Riga",
    "state": "Riga",
    "postal_code": "LV-1010",
    "country": "Latvia",
    "country_code": "LV",
    "currency": "EUR",
    "person_name": "Līga Liepiņa",
    "gender": "Female",
    "phone_number": "+37126123459"
  },
  {
    "street_address": "89 Dzirnavu iela",
    "street_name": "Dzirnavu iela",
    "building_number": "89",
    "city": "Riga",
    "state": "Riga",
    "postal_code": "LV-1010",
    "country": "Latvia",
    "country_code": "LV",
    "currency": "EUR",
    "person_name": "Mārtiņš Krūmiņš",
    "gender": "Male",
    "phone_number": "+37126123460"
  },
  {
    "street_address": "56 Lielā iela",
    "street_name": "Lielā iela",
    "building_number": "56",
    "city": "Liepaja",
    "state": "Liepaja",
    "postal_code": "LV-3401",
    "country": "Latvia",
    "country_code": "LV",
    "currency": "EUR",
    "person_name": "Elīna Vītoliņa",
    "gender": "Female",
    "phone_number": "+37126123461"
  },
  {
    "street_address": "23 Rožu iela",
    "street_name": "Rožu iela",
    "building_number": "23",
    "city": "Liepaja",
    "state": "Liepaja",
    "postal_code": "LV-3401",
    "country": "Latvia",
    "country_code": "LV",
    "currency": "EUR",
    "person_name": "Andris Pētersons",
    "gender": "Male",
    "phone_number": "+37126123462"
  },
  {
    "street_address": "67 Graudu iela",
    "street_name": "Graudu iela",
    "building_number": "67",
    "city": "Liepaja",
    "state": "Liepaja",
    "postal_code": "LV-3401",
    "country": "Latvia",
    "country_code": "LV",
    "currency": "EUR",
    "person_name": "Zane Balode",
    "gender": "Female",
    "phone_number": "+37126123463"
  },
  {
    "street_address": "21 Jūras iela",
    "street_name": "Jūras iela",
    "building_number": "21",
    "city": "Liepaja",
    "state": "Liepaja",
    "postal_code": "LV-3401",
    "country": "Latvia",
    "country_code": "LV",
    "currency": "EUR",
    "person_name": "Edgars Zariņš",
    "gender": "Male",
    "phone_number": "+37126123464"
  },
  {
    "street_address": "95 Tirgoņu iela",
    "street_name": "Tirgoņu iela",
    "building_number": "95",
    "city": "Liepaja",
    "state": "Liepaja",
    "postal_code": "LV-3401",
    "country": "Latvia",
    "country_code": "LV",
    "currency": "EUR",
    "person_name": "Inese Ozola",
    "gender": "Female",
    "phone_number": "+37126123465"
  },
  {
    "street_address": "42 Dārza iela",
    "street_name": "Dārza iela",
    "building_number": "42",
    "city": "Jelgava",
    "state": "Jelgava",
    "postal_code": "LV-3001",
    "country": "Latvia",
    "country_code": "LV",
    "currency": "EUR",
    "person_name": "Rihards Vītols",
    "gender": "Male",
    "phone_number": "+37126123466"
  },
  {
    "street_address": "76 Pasta iela",
    "street_name": "Pasta iela",
    "building_number": "76",
    "city": "Jelgava",
    "state": "Jelgava",
    "postal_code": "LV-3001",
    "country": "Latvia",
    "country_code": "LV",
    "currency": "EUR",
    "person_name": "Laura Briede",
    "gender": "Female",
    "phone_number": "+37126123467"
  },
  {
    "street_address": "54 Uzvaras iela",
    "street_name": "Uzvaras iela",
    "building_number": "54",
    "city": "Jelgava",
    "state": "Jelgava",
    "postal_code": "LV-3001",
    "country": "Latvia",
    "country_code": "LV",
    "currency": "EUR",
    "person_name": "Toms Leitis",
    "gender": "Male",
    "phone_number": "+37126123468"
  },
  {
    "street_address": "123 Lielā iela",
    "street_name": "Lielā iela",
    "building_number": "123",
    "city": "Daugavpils",
    "state": "Daugavpils",
    "postal_code": "LV-5401",
    "country": "Latvia",
    "country_code": "LV",
    "currency": "EUR",
    "person_name": "Kristīne Ozoliņa",
    "gender": "Female",
    "phone_number": "+37126123469"
  },
  {
    "street_address": "38 Rīgas iela",
    "street_name": "Rīgas iela",
    "building_number": "38",
    "city": "Daugavpils",
    "state": "Daugavpils",
    "postal_code": "LV-5401",
    "country": "Latvia",
    "country_code": "LV",
    "currency": "EUR",
    "person_name": "Dāvis Bērziņš",
    "gender": "Male",
    "phone_number": "+37126123470"
  },
  {
    "street_address": "62 Vienības iela",
    "street_name": "Vienības iela",
    "building_number": "62",
    "city": "Daugavpils",
    "state": "Daugavpils",
    "postal_code": "LV-5401",
    "country": "Latvia",
    "country_code": "LV",
    "currency": "EUR",
    "person_name": "Elza Liepiņa",
    "gender": "Female",
    "phone_number": "+37126123471"
  },
  {
    "street_address": "15 Cēsu iela",
    "street_name": "Cēsu iela",
    "building_number": "15",
    "city": "Daugavpils",
    "state": "Daugavpils",
    "postal_code": "LV-5401",
    "country": "Latvia",
    "country_code": "LV",
    "currency": "EUR",
    "person_name": "Artūrs Krūmiņš",
    "gender": "Male",
    "phone_number": "+37126123472"
  },
  {
    "street_address": "100 Kr. Valdemāra iela",
    "street_name": "Kr. Valdemāra iela",
    "building_number": "100",
    "city": "Ventspils",
    "state": "Ventspils",
    "postal_code": "LV-3601",
    "country": "Latvia",
    "country_code": "LV",
    "currency": "EUR",
    "person_name": "Santa Vītola",
    "gender": "Female",
    "phone_number": "+37126123473"
  },
  {
    "street_address": "34 Kuldīgas iela",
    "street_name": "Kuldīgas iela",
    "building_number": "34",
    "city": "Ventspils",
    "state": "Ventspils",
    "postal_code": "LV-3601",
    "country": "Latvia",
    "country_code": "LV",
    "currency": "EUR",
    "person_name": "Juris Ozols",
    "gender": "Male",
    "phone_number": "+37126123474"
  },
  {
    "street_address": "89 Lielais prospekts",
    "street_name": "Lielais prospekts",
    "building_number": "89",
    "city": "Ventspils",
    "state": "Ventspils",
    "postal_code": "LV-3601",
    "country": "Latvia",
    "country_code": "LV",
    "currency": "EUR",
    "person_name": "Māra Balode",
    "gender": "Female",
    "phone_number": "+37126123475"
  },
  {
    "street_address": "25 Pils iela",
    "street_name": "Pils iela",
    "building_number": "25",
    "city": "Ventspils",
    "state": "Ventspils",
    "postal_code": "LV-3601",
    "country": "Latvia",
    "country_code": "LV",
    "currency": "EUR",
    "person_name": "Valdis Zariņš",
    "gender": "Male",
    "phone_number": "+37126123476"
  },
  {
    "street_address": "67 Talsu iela",
    "street_name": "Talsu iela",
    "building_number": "67",
    "city": "Jurmala",
    "state": "Jurmala",
    "postal_code": "LV-2015",
    "country": "Latvia",
    "country_code": "LV",
    "currency": "EUR",
    "person_name": "Ilze Pētersone",
    "gender": "Female",
    "phone_number": "+37126123477"
  },
  {
    "street_address": "12 Jomas iela",
    "street_name": "Jomas iela",
    "building_number": "12",
    "city": "Jurmala",
    "state": "Jurmala",
    "postal_code": "LV-2015",
    "country": "Latvia",
    "country_code": "LV",
    "currency": "EUR",
    "person_name": "Gints Vītoliņš",
    "gender": "Male",
    "phone_number": "+37126123478"
  }
]